ntnx_storage_py_client/__init__.py
ntnx_storage_py_client/api_client.py
ntnx_storage_py_client/api_response.py
ntnx_storage_py_client/configuration.py
ntnx_storage_py_client/rest.py
ntnx_storage_py_client/Ntnx/__init__.py
ntnx_storage_py_client/Ntnx/OneOfcommon/__init__.py
ntnx_storage_py_client/Ntnx/OneOfcommon/v1/__init__.py
ntnx_storage_py_client/Ntnx/OneOfcommon/v1/config/KVPairvalue.py
ntnx_storage_py_client/Ntnx/OneOfcommon/v1/config/__init__.py
ntnx_storage_py_client/Ntnx/OneOfstorage/__init__.py
ntnx_storage_py_client/Ntnx/OneOfstorage/v4/__init__.py
ntnx_storage_py_client/Ntnx/OneOfstorage/v4/config/DataStoreResponsedata.py
ntnx_storage_py_client/Ntnx/OneOfstorage/v4/config/DataStoreTaskResponsedata.py
ntnx_storage_py_client/Ntnx/OneOfstorage/v4/config/StorageContainerResponsedata.py
ntnx_storage_py_client/Ntnx/OneOfstorage/v4/config/StorageContainerTaskResponsedata.py
ntnx_storage_py_client/Ntnx/OneOfstorage/v4/config/StorageContainersResponsedata.py
ntnx_storage_py_client/Ntnx/OneOfstorage/v4/config/__init__.py
ntnx_storage_py_client/Ntnx/OneOfstorage/v4/error/ErrorResponseerror.py
ntnx_storage_py_client/Ntnx/OneOfstorage/v4/error/__init__.py
ntnx_storage_py_client/Ntnx/common/__init__.py
ntnx_storage_py_client/Ntnx/common/v1/__init__.py
ntnx_storage_py_client/Ntnx/common/v1/config/FQDN.py
ntnx_storage_py_client/Ntnx/common/v1/config/Flag.py
ntnx_storage_py_client/Ntnx/common/v1/config/IPAddressOrFQDN.py
ntnx_storage_py_client/Ntnx/common/v1/config/IPv4Address.py
ntnx_storage_py_client/Ntnx/common/v1/config/IPv6Address.py
ntnx_storage_py_client/Ntnx/common/v1/config/KVPair.py
ntnx_storage_py_client/Ntnx/common/v1/config/Message.py
ntnx_storage_py_client/Ntnx/common/v1/config/MessageSeverity.py
ntnx_storage_py_client/Ntnx/common/v1/config/TenantAwareModel.py
ntnx_storage_py_client/Ntnx/common/v1/config/__init__.py
ntnx_storage_py_client/Ntnx/common/v1/response/ApiLink.py
ntnx_storage_py_client/Ntnx/common/v1/response/ApiResponseMetadata.py
ntnx_storage_py_client-4.0.2a3.dist-info/LICENSE.txt
ntnx_storage_py_client-4.0.2a3.dist-info/METADATA
ntnx_storage_py_client-4.0.2a3.dist-info/WHEEL
ntnx_storage_py_client-4.0.2a3.dist-info/top_level.txt
ntnx_storage_py_client-4.0.2a3.dist-info/RECORD
