Metadata-Version: 2.1
Name: ntnx-storage-py-client
Version: 4.0.2a3
Summary: Nutanix Storage Versioned APIs
Home-page: 
Author-email: sdk@nutanix.com
Keywords: Nutanix,v4,SDK,Nutanix Storage Versioned APIs
License-File: LICENSE.txt
